Workbook

Sheet Indice
A1: Análisis Financiero de Ventas 2022 — Guía del libro
A2: Base: 1.901 transacciones de venta de equipos tecnológicos (celulares, portátiles, PC de mesa), enero–diciembre 2022.
A4: # | B4: Hoja | C4: Qué contiene | D4: Por qué importa
A5: 0 | B5: Indice | C5: Esta hoja. Explica el propósito de cada pestaña y cómo se conectan entre sí.
A6: 1 | B6: Datos | C6: Base de datos original limpiada (textos sin espacios ni mayúsculas inconsistentes) y con columnas calculadas: Ventas, Costo Total, Utilidad Bruta, Margen % y Mes. | D6: Es la única fuente de datos: todas las demás hojas calculan sobre esta con fórmulas (SUMIFS/COUNTIFS), así que si se agregan filas nuevas, el resto del libro se actualiza solo.
A7: 2 | B7: Ventas Mensuales | C7: Ventas, utilidad y margen por mes, más una previsión de ventas para ene–mar 2023 por regresión lineal (FORECAST). | D7: Detectar estacionalidad y anticipar flujo de caja. Diciembre se normaliza (solo hay datos hasta el día 14) para no distorsionar la tendencia.
A8: 3 | B8: Producto y Marca | C8: Ventas, utilidad y margen por producto y por marca, ordenados de mayor a menor. | D8: Identifica qué productos sostienen la utilidad real (no solo el volumen) y guía decisiones de compra e inventario.
A9: 4 | B9: Clientes | C9: Ventas por cliente, participación %, acumulado y un índice de concentración (HHI). | D9: La empresa vende solo a 4 clientes: cuantifica el riesgo de depender de uno solo.
A10: 5 | B10: Vendedores | C10: Ventas, utilidad, número de transacciones y ticket promedio por empleado, con ranking. | D10: Base objetiva para evaluar desempeño comercial y comisiones.
A11: 6 | B11: Segmentacion | C11: Cruces por ciudad, transportadora, tipo de cliente y forma de pago. | D11: Muestra dependencia logística y de crédito: el 81% de las ventas son a crédito.
A12: 7 | B12: Alertas Margen | C12: Semáforo por producto frente a un margen objetivo editable, con la utilidad que se deja de ganar. | D12: Prioriza qué productos renegociar o dejar de vender: Galaxy s23 o Intel Corei7 venden bien pero ganan casi nada.
A13: 8 | B13: Escenarios | C13: Simulador: cuánto cambia la utilidad si sube el margen o varían las ventas. | D13: Convierte el diagnóstico en metas: cada punto de margen recuperado tiene un valor en pesos.
A14: 9 | B14: Estacionalidad | C14: Ventas por trimestre e índice mensual frente al promedio (diciembre normalizado). | D14: Explica el pico de mayo y el valle de julio; ayuda a planear inventario y caja.
A15: 10 | B15: Ratios Financieros | C15: Panel de indicadores clave (margen, ticket promedio, concentración, participación de crédito, etc.) enlazados a las demás hojas. | D15: Resumen ejecutivo de una sola pantalla para tomar decisiones rápido.
A17: Notas de limpieza de datos aplicadas
A18: • Se unificaron variantes de texto: "crédito"/"Crédito", "A "/"A" (espacios), "Ing.Industrial"/"Ing. Industrial".
A19: • Se validó que no existen valores nulos en ninguna columna (1.901 filas, 0 vacíos).
A20: • Diciembre 2022 solo tiene registros hasta el día 14: cualquier caída de fin de año en el mes debe leerse con cautela.
A21: • Definiciones: Ventas = Precio unitario × Cantidad. Costo Total = Costo × Cantidad. Utilidad Bruta = Ventas − Costo Total.

Sheet Datos
A1: Datos — Base de ventas limpia (fuente única del libro). Ventas = Precio×Cantidad · Costo Total = Costo×Cantidad · Utilidad Bruta = Ventas−Costo Total · columnas Q,R,S,T,U son fórmulas.
A2: Fecha | B2: Idventa | C2: Producto | D2: Tipo | E2: Marca | F2: Precio (u) | G2: Costo (u) | H2: Cant (u) | I2: Pago cliente | J2: Cliente | K2: Ciudad cliente | L2: Transportadora | M2: Tipo cliente | N2: Empleado | O2: Area | P2: Profesion | Q2: Ventas | R2: Costo Total | S2: Utilidad Bruta | T2: Margen % | U2: Mes
A3: 44562 | B3: PP_1 | C3: iPhone 11 | D3: Celuar | E3: Apple | F3: 3048952 | G3: 2560000 | H3: 4 | I3: Crédito | J3: Smart S.A.S | K3: Medellín | L3: Fluvial | M3: A | N3: Diego | O3: Compras | P3: Ing. Industrial | Q3: =F3*H3 -> 12195808 | R3: =G3*H3 -> 10240000 | S3: =Q3-R3 -> 1955808 | T3: =IFERROR(S3/Q3,0) -> 0.16036723 | U3: =TEXT(A3,"yyyy-mm") -> 2022-01
A4: 44562 | B4: PP_2 | C4: Xiaomi 13T | D4: Celuar | E4: Xiaomi | F4: 1870000 | G4: 1650000 | H4: 11 | I4: Crédito | J4: Asociados LTDA | K4: Bogotá | L4: Terrestre | M4: A | N4: Diego | O4: Compras | P4: Ing. Industrial | Q4: =F4*H4 -> 20570000 | R4: =G4*H4 -> 18150000 | S4: =Q4-R4 -> 2420000 | T4: =IFERROR(S4/Q4,0) -> 0.11764706 | U4: =TEXT(A4,"yyyy-mm") -> 2022-01
A5: 44562 | B5: PP_3 | C5: Vivo x80 | D5: Celuar | E5: Vivo | F5: 2600000 | G5: 2300000 | H5: 13 | I5: Contado | J5: FullStark | K5: Bucaramanga | L5: Aereo | M5: B | N5: Diego | O5: Compras | P5: Ing. Industrial | Q5: =F5*H5 -> 33800000 | R5: =G5*H5 -> 29900000 | S5: =Q5-R5 -> 3900000 | T5: =IFERROR(S5/Q5,0) -> 0.11538462 | U5: =TEXT(A5,"yyyy-mm") -> 2022-01
A6: 44563 | B6: PP_4 | C6: Xiaomi redmi 8 | D6: Celuar | E6: Xiaomi | F6: 3577480 | G6: 3100000 | H6: 23 | I6: Crédito | J6: Asociados LTDA | K6: Bogotá | L6: Terrestre | M6: A | N6: Matias | O6: Almacen | P6: Administrador | Q6: =F6*H6 -> 82282040 | R6: =G6*H6 -> 71300000 | S6: =Q6-R6 -> 10982040 | T6: =IFERROR(S6/Q6,0) -> 0.13346825 | U6: =TEXT(A6,"yyyy-mm") -> 2022-01
A7: 44563 | B7: PP_5 | C7: Galaxy jpro | D7: Celuar | E7: Samsum | F7: 4969724 | G7: 4121560 | H7: 20 | I7: Crédito | J7: Asociados LTDA | K7: Bogotá | L7: Terrestre | M7: A | N7: Daniela | O7: Despachos | P7: Contador | Q7: =F7*H7 -> 99394480 | R7: =G7*H7 -> 82431200 | S7: =Q7-R7 -> 16963280 | T7: =IFERROR(S7/Q7,0) -> 0.17066622 | U7: =TEXT(A7,"yyyy-mm") -> 2022-01
A8: 44564 | B8: PP_6 | C8: iPhone 13 pro | D8: Celuar | E8: Apple | F8: 3319925 | G8: 2800000 | H8: 9 | I8: Contado | J8: FullStark | K8: Bucaramanga | L8: Aereo | M8: B | N8: Paola | O8: Logística | P8: Ing. Sistemas | Q8: =F8*H8 -> 29879325 | R8: =G8*H8 -> 25200000 | S8: =Q8-R8 -> 4679325 | T8: =IFERROR(S8/Q8,0) -> 0.15660745 | U8: =TEXT(A8,"yyyy-mm") -> 2022-01
A9: 44564 | B9: PP_7 | C9: iPhone 13 pro max | D9: Celuar | E9: Apple | F9: 4757880 | G9: 3450000 | H9: 7 | I9: Crédito | J9: Asociados LTDA | K9: Bogotá | L9: Terrestre | M9: A | N9: Hernan | O9: Compras | P9: Administrador | Q9: =F9*H9 -> 33305160 | R9: =G9*H9 -> 24150000 | S9: =Q9-R9 -> 9155160 | T9: =IFERROR(S9/Q9,0) -> 0.27488713 | U9: =TEXT(A9,"yyyy-mm") -> 2022-01
A10: 44564 | B10: PP_8 | C10: 13ultra | D10: Celuar | E10: Xiaomi | F10: 3545808 | G10: 3350000 | H10: 12 | I10: Crédito | J10: Distribuidora Oriente | K10: Cali | L10: Terrestre | M10: A | N10: Matias | O10: Almacen | P10: Administrador | Q10: =F10*H10 -> 42549696 | R10: =G10*H10 -> 40200000 | S10: =Q10-R10 -> 2349696 | T10: =IFERROR(S10/Q10,0) -> 0.055222392 | U10: =TEXT(A10,"yyyy-mm") -> 2022-01
A11: 44564 | B11: PP_9 | C11: Galaxy s23 | D11: Celuar | E11: Samsum | F11: 4200743 | G11: 4101000 | H11: 12 | I11: Contado | J11: FullStark | K11: Bucaramanga | L11: Aereo | M11: B | N11: Diego | O11: Compras | P11: Ing. Industrial | Q11: =F11*H11 -> 50408916 | R11: =G11*H11 -> 49212000 | S11: =Q11-R11 -> 1196916 | T11: =IFERROR(S11/Q11,0) -> 0.023744133 | U11: =TEXT(A11,"yyyy-mm") -> 2022-01
A12: 44564 | B12: PP_10 | C12: Lenovo 14IGL7 | D12: Portátil | E12: Lenovo | F12: 8220549 | G12: 6500000 | H12: 13 | I12: Crédito | J12: Asociados LTDA | K12: Bogotá | L12: Terrestre | M12: A | N12: Matias | O12: Almacen | P12: Administrador | Q12: =F12*H12 -> 106867137 | R12: =G12*H12 -> 84500000 | S12: =Q12-R12 -> 22367137 | T12: =IFERROR(S12/Q12,0) -> 0.20929855 | U12: =TEXT(A12,"yyyy-mm") -> 2022-01
A13: 44564 | B13: PP_11 | C13: Gaming F15 | D13: Portátil | E13: Asus | F13: 7687274 | G13: 6500000 | H13: 9 | I13: Crédito | J13: Asociados LTDA | K13: Bogotá | L13: Terrestre | M13: A | N13: Lina | O13: Ventas | P13: Ing. Sistemas | Q13: =F13*H13 -> 69185466 | R13: =G13*H13 -> 58500000 | S13: =Q13-R13 -> 10685466 | T13: =IFERROR(S13/Q13,0) -> 0.15444669 | U13: =TEXT(A13,"yyyy-mm") -> 2022-01
A14: 44564 | B14: PP_12 | C14: ASPIRE 3 | D14: Portátil | E14: Acer | F14: 5684211 | G14: 4300000 | H14: 9 | I14: Crédito | J14: Asociados LTDA | K14: Bogotá | L14: Terrestre | M14: A | N14: Hernan | O14: Compras | P14: Administrador | Q14: =F14*H14 -> 51157899 | R14: =G14*H14 -> 38700000 | S14: =Q14-R14 -> 12457899 | T14: =IFERROR(S14/Q14,0) -> 0.24351858 | U14: =TEXT(A14,"yyyy-mm") -> 2022-01
... A1903: 44909 | B1903: PP_1900 | C1903: Celular Donalis | D1903: Portátil | E1903: Lenovo | F1903: 8220549 | G1903: 6500000 | H1903: 21 | I1903: Contado | J1903: FullStark | K1903: Bucaramanga | L1903: Aereo | M1903: B | N1903: Matias | O1903: Almacen | P1903: Administrador | Q1903: =F1903*H1903 -> 172631529 | R1903: =G1903*H1903 -> 136500000 | S1903: =Q1903-R1903 -> 36131529 | T1903: =IFERROR(S1903/Q1903,0) -> 0.20929855 | U1903: =TEXT(A1903,"yyyy-mm") -> 2022-12

Sheet Ventas Mensuales
A1: Ventas Mensuales — Tendencia y previsión (ene–mar 2023)
A2: Diciembre se normaliza a 30 días (solo hay datos hasta el 14) antes de calcular la tendencia. La previsión usa FORECAST (regresión lineal) sobre las ventas normalizadas.
A3: Mes | B3: Ventas | C3: Utilidad Bruta | D3: Margen % | E3: Transacciones | F3: Unidades | G3: Ventas Normalizada | H3: Tendencia / Previsión
A4: 2022-01 | B4: =SUMIFS(Datos!$Q$3:$Q$1903,Datos!$U$3:$U$1903,$A4) -> 9738965526 | C4: =SUMIFS(Datos!$S$3:$S$1903,Datos!$U$3:$U$1903,$A4) -> 1548066166 | D4: =IFERROR(C4/B4,0) -> 0.15895591 | E4: =COUNTIFS(Datos!$U$3:$U$1903,$A4) -> 180 | F4: =SUMIFS(Datos!$H$3:$H$1903,Datos!$U$3:$U$1903,$A4) -> 2302 | G4: =IF($A4="2022-12",B4*30/14,B4) -> 9738965526 | H4: =FORECAST($I4,$G$4:$G$15,$I$4:$I$15) -> 9.4987539e+09 | I4: 1
A5: 2022-02 | B5: =SUMIFS(Datos!$Q$3:$Q$1903,Datos!$U$3:$U$1903,$A5) -> 7667494170 | C5: =SUMIFS(Datos!$S$3:$S$1903,Datos!$U$3:$U$1903,$A5) -> 1210083850 | D5: =IFERROR(C5/B5,0) -> 0.15781999 | E5: =COUNTIFS(Datos!$U$3:$U$1903,$A5) -> 154 | F5: =SUMIFS(Datos!$H$3:$H$1903,Datos!$U$3:$U$1903,$A5) -> 1846 | G5: =IF($A5="2022-12",B5*30/14,B5) -> 7667494170 | H5: =FORECAST($I5,$G$4:$G$15,$I$4:$I$15) -> 9.4224291e+09 | I5: 2
A6: 2022-03 | B6: =SUMIFS(Datos!$Q$3:$Q$1903,Datos!$U$3:$U$1903,$A6) -> 9139607974 | C6: =SUMIFS(Datos!$S$3:$S$1903,Datos!$U$3:$U$1903,$A6) -> 1313201894 | D6: =IFERROR(C6/B6,0) -> 0.14368252 | E6: =COUNTIFS(Datos!$U$3:$U$1903,$A6) -> 162 | F6: =SUMIFS(Datos!$H$3:$H$1903,Datos!$U$3:$U$1903,$A6) -> 2182 | G6: =IF($A6="2022-12",B6*30/14,B6) -> 9139607974 | H6: =FORECAST($I6,$G$4:$G$15,$I$4:$I$15) -> 9.3461043e+09 | I6: 3
A7: 2022-04 | B7: =SUMIFS(Datos!$Q$3:$Q$1903,Datos!$U$3:$U$1903,$A7) -> 11045631654 | C7: =SUMIFS(Datos!$S$3:$S$1903,Datos!$U$3:$U$1903,$A7) -> 1813784534 | D7: =IFERROR(C7/B7,0) -> 0.16420831 | E7: =COUNTIFS(Datos!$U$3:$U$1903,$A7) -> 178 | F7: =SUMIFS(Datos!$H$3:$H$1903,Datos!$U$3:$U$1903,$A7) -> 2480 | G7: =IF($A7="2022-12",B7*30/14,B7) -> 11045631654 | H7: =FORECAST($I7,$G$4:$G$15,$I$4:$I$15) -> 9.2697796e+09 | I7: 4
A8: 2022-05 | B8: =SUMIFS(Datos!$Q$3:$Q$1903,Datos!$U$3:$U$1903,$A8) -> 13800339040 | C8: =SUMIFS(Datos!$S$3:$S$1903,Datos!$U$3:$U$1903,$A8) -> 2252783120 | D8: =IFERROR(C8/B8,0) -> 0.16324114 | E8: =COUNTIFS(Datos!$U$3:$U$1903,$A8) -> 236 | F8: =SUMIFS(Datos!$H$3:$H$1903,Datos!$U$3:$U$1903,$A8) -> 3194 | G8: =IF($A8="2022-12",B8*30/14,B8) -> 13800339040 | H8: =FORECAST($I8,$G$4:$G$15,$I$4:$I$15) -> 9.1934548e+09 | I8: 5
A9: 2022-06 | B9: =SUMIFS(Datos!$Q$3:$Q$1903,Datos!$U$3:$U$1903,$A9) -> 8076808966 | C9: =SUMIFS(Datos!$S$3:$S$1903,Datos!$U$3:$U$1903,$A9) -> 1205619366 | D9: =IFERROR(C9/B9,0) -> 0.14926927 | E9: =COUNTIFS(Datos!$U$3:$U$1903,$A9) -> 164 | F9: =SUMIFS(Datos!$H$3:$H$1903,Datos!$U$3:$U$1903,$A9) -> 2016 | G9: =IF($A9="2022-12",B9*30/14,B9) -> 8076808966 | H9: =FORECAST($I9,$G$4:$G$15,$I$4:$I$15) -> 9.1171301e+09 | I9: 6
A10: 2022-07 | B10: =SUMIFS(Datos!$Q$3:$Q$1903,Datos!$U$3:$U$1903,$A10) -> 5985626746 | C10: =SUMIFS(Datos!$S$3:$S$1903,Datos!$U$3:$U$1903,$A10) -> 943434346 | D10: =IFERROR(C10/B10,0) -> 0.15761663 | E10: =COUNTIFS(Datos!$U$3:$U$1903,$A10) -> 114 | F10: =SUMIFS(Datos!$H$3:$H$1903,Datos!$U$3:$U$1903,$A10) -> 1466 | G10: =IF($A10="2022-12",B10*30/14,B10) -> 5985626746 | H10: =FORECAST($I10,$G$4:$G$15,$I$4:$I$15) -> 9.0408053e+09 | I10: 7
A11: 2022-08 | B11: =SUMIFS(Datos!$Q$3:$Q$1903,Datos!$U$3:$U$1903,$A11) -> 7802299454 | C11: =SUMIFS(Datos!$S$3:$S$1903,Datos!$U$3:$U$1903,$A11) -> 1159634974 | D11: =IFERROR(C11/B11,0) -> 0.14862733 | E11: =COUNTIFS(Datos!$U$3:$U$1903,$A11) -> 150 | F11: =SUMIFS(Datos!$H$3:$H$1903,Datos!$U$3:$U$1903,$A11) -> 1894 | G11: =IF($A11="2022-12",B11*30/14,B11) -> 7802299454 | H11: =FORECAST($I11,$G$4:$G$15,$I$4:$I$15) -> 8.9644805e+09 | I11: 8
A12: 2022-09 | B12: =SUMIFS(Datos!$Q$3:$Q$1903,Datos!$U$3:$U$1903,$A12) -> 7381244630 | C12: =SUMIFS(Datos!$S$3:$S$1903,Datos!$U$3:$U$1903,$A12) -> 1198338710 | D12: =IFERROR(C12/B12,0) -> 0.16234914 | E12: =COUNTIFS(Datos!$U$3:$U$1903,$A12) -> 152 | F12: =SUMIFS(Datos!$H$3:$H$1903,Datos!$U$3:$U$1903,$A12) -> 1764 | G12: =IF($A12="2022-12",B12*30/14,B12) -> 7381244630 | H12: =FORECAST($I12,$G$4:$G$15,$I$4:$I$15) -> 8.8881558e+09 | I12: 9
A13: 2022-10 | B13: =SUMIFS(Datos!$Q$3:$Q$1903,Datos!$U$3:$U$1903,$A13) -> 8688965074 | C13: =SUMIFS(Datos!$S$3:$S$1903,Datos!$U$3:$U$1903,$A13) -> 1386024914 | D13: =IFERROR(C13/B13,0) -> 0.15951554 | E13: =COUNTIFS(Datos!$U$3:$U$1903,$A13) -> 162 | F13: =SUMIFS(Datos!$H$3:$H$1903,Datos!$U$3:$U$1903,$A13) -> 2044 | G13: =IF($A13="2022-12",B13*30/14,B13) -> 8688965074 | H13: =FORECAST($I13,$G$4:$G$15,$I$4:$I$15) -> 8.811831e+09 | I13: 10
A14: 2022-11 | B14: =SUMIFS(Datos!$Q$3:$Q$1903,Datos!$U$3:$U$1903,$A14) -> 9978997204 | C14: =SUMIFS(Datos!$S$3:$S$1903,Datos!$U$3:$U$1903,$A14) -> 1524078484 | D14: =IFERROR(C14/B14,0) -> 0.15272862 | E14: =COUNTIFS(Datos!$U$3:$U$1903,$A14) -> 168 | F14: =SUMIFS(Datos!$H$3:$H$1903,Datos!$U$3:$U$1903,$A14) -> 2288 | G14: =IF($A14="2022-12",B14*30/14,B14) -> 9978997204 | H14: =FORECAST($I14,$G$4:$G$15,$I$4:$I$15) -> 8.7355063e+09 | I14: 11
A15: 2022-12 | B15: =SUMIFS(Datos!$Q$3:$Q$1903,Datos!$U$3:$U$1903,$A15) -> 4499428125 | C15: =SUMIFS(Datos!$S$3:$S$1903,Datos!$U$3:$U$1903,$A15) -> 704698445 | D15: =IFERROR(C15/B15,0) -> 0.15661956 | E15: =COUNTIFS(Datos!$U$3:$U$1903,$A15) -> 81 | F15: =SUMIFS(Datos!$H$3:$H$1903,Datos!$U$3:$U$1903,$A15) -> 1065 | G15: =IF($A15="2022-12",B15*30/14,B15) -> 9.6416317e+09 | H15: =FORECAST($I15,$G$4:$G$15,$I$4:$I$15) -> 8.6591815e+09 | I15: 12
A16: 2023-01 | H16: =FORECAST($I16,$G$4:$G$15,$I$4:$I$15) -> 8.5828567e+09 | I16: 13
A17: 2023-02 | H17: =FORECAST($I17,$G$4:$G$15,$I$4:$I$15) -> 8.506532e+09 | I17: 14
A18: 2023-03 | H18: =FORECAST($I18,$G$4:$G$15,$I$4:$I$15) -> 8.4302072e+09 | I18: 15
A20: Nota: la columna I (índice 1–15) es un auxiliar para la regresión; puede ocultarse.

Sheet Producto y Marca
A1: Producto y Marca — Ventas, utilidad y margen
A2: Ordenado de mayor a menor por ventas. El margen % revela qué productos son rentables de verdad, no solo los de mayor volumen.
A3: Producto | B3: Ventas | C3: Utilidad Bruta | D3: Margen % | E3: Unidades | F3: Ticket Promedio
A4: Lenovo 14IGL7 | B4: =SUMIFS(Datos!$Q$3:$Q$1903,Datos!$C$3:$C$1903,$A4) -> 9897540996 | C4: =SUMIFS(Datos!$S$3:$S$1903,Datos!$C$3:$C$1903,$A4) -> 2071540996 | D4: =IFERROR(C4/B4,0) -> 0.20929855 | E4: =SUMIFS(Datos!$H$3:$H$1903,Datos!$C$3:$C$1903,$A4) -> 1204 | F4: =IFERROR(B4/E4,0) -> 8220549
A5: MacBook Pro | B5: =SUMIFS(Datos!$Q$3:$Q$1903,Datos!$C$3:$C$1903,$A5) -> 9468071808 | C5: =SUMIFS(Datos!$S$3:$S$1903,Datos!$C$3:$C$1903,$A5) -> 757031808 | D5: =IFERROR(C5/B5,0) -> 0.079956281 | E5: =SUMIFS(Datos!$H$3:$H$1903,Datos!$C$3:$C$1903,$A5) -> 1664 | F5: =IFERROR(B5/E5,0) -> 5689947
A6: ASUS AIO V | B6: =SUMIFS(Datos!$Q$3:$Q$1903,Datos!$C$3:$C$1903,$A6) -> 8806137912 | C6: =SUMIFS(Datos!$S$3:$S$1903,Datos!$C$3:$C$1903,$A6) -> 865545912 | D6: =IFERROR(C6/B6,0) -> 0.098288934 | E6: =SUMIFS(Datos!$H$3:$H$1903,Datos!$C$3:$C$1903,$A6) -> 1782 | F6: =IFERROR(B6/E6,0) -> 4941716
A7: Gaming F15 | B7: =SUMIFS(Datos!$Q$3:$Q$1903,Datos!$C$3:$C$1903,$A7) -> 8517499592 | C7: =SUMIFS(Datos!$S$3:$S$1903,Datos!$C$3:$C$1903,$A7) -> 1315499592 | D7: =IFERROR(C7/B7,0) -> 0.15444669 | E7: =SUMIFS(Datos!$H$3:$H$1903,Datos!$C$3:$C$1903,$A7) -> 1108 | F7: =IFERROR(B7/E7,0) -> 7687274
A8: 15 Pulgadas Ip1 Athlon | B8: =SUMIFS(Datos!$Q$3:$Q$1903,Datos!$C$3:$C$1903,$A8) -> 6585570108 | C8: =SUMIFS(Datos!$S$3:$S$1903,Datos!$C$3:$C$1903,$A8) -> 2482170108 | D8: =IFERROR(C8/B8,0) -> 0.37691044 | E8: =SUMIFS(Datos!$H$3:$H$1903,Datos!$C$3:$C$1903,$A8) -> 1954 | F8: =IFERROR(B8/E8,0) -> 3370302
A9: Xiaomi redmi 8 | B9: =SUMIFS(Datos!$Q$3:$Q$1903,Datos!$C$3:$C$1903,$A9) -> 6367914400 | C9: =SUMIFS(Datos!$S$3:$S$1903,Datos!$C$3:$C$1903,$A9) -> 849914400 | D9: =IFERROR(C9/B9,0) -> 0.13346825 | E9: =SUMIFS(Datos!$H$3:$H$1903,Datos!$C$3:$C$1903,$A9) -> 1780 | F9: =IFERROR(B9/E9,0) -> 3577480
A10: MacBook Air | B10: =SUMIFS(Datos!$Q$3:$Q$1903,Datos!$C$3:$C$1903,$A10) -> 6033325368 | C10: =SUMIFS(Datos!$S$3:$S$1903,Datos!$C$3:$C$1903,$A10) -> 857349368 | D10: =IFERROR(C10/B10,0) -> 0.14210229 | E10: =SUMIFS(Datos!$H$3:$H$1903,Datos!$C$3:$C$1903,$A10) -> 1256 | F10: =IFERROR(B10/E10,0) -> 4803603
A11: Intel Corei7 | B11: =SUMIFS(Datos!$Q$3:$Q$1903,Datos!$C$3:$C$1903,$A11) -> 5161483346 | C11: =SUMIFS(Datos!$S$3:$S$1903,Datos!$C$3:$C$1903,$A11) -> 281263346 | D11: =IFERROR(C11/B11,0) -> 0.054492735 | E11: =SUMIFS(Datos!$H$3:$H$1903,Datos!$C$3:$C$1903,$A11) -> 998 | F11: =IFERROR(B11/E11,0) -> 5171827
A12: Galaxy jpro | B12: =SUMIFS(Datos!$Q$3:$Q$1903,Datos!$C$3:$C$1903,$A12) -> 4949845104 | C12: =SUMIFS(Datos!$S$3:$S$1903,Datos!$C$3:$C$1903,$A12) -> 844771344 | D12: =IFERROR(C12/B12,0) -> 0.17066622 | E12: =SUMIFS(Datos!$H$3:$H$1903,Datos!$C$3:$C$1903,$A12) -> 996 | F12: =IFERROR(B12/E12,0) -> 4969724
A13: JANUS | B13: =SUMIFS(Datos!$Q$3:$Q$1903,Datos!$C$3:$C$1903,$A13) -> 4392824184 | C13: =SUMIFS(Datos!$S$3:$S$1903,Datos!$C$3:$C$1903,$A13) -> 982076184 | D13: =IFERROR(C13/B13,0) -> 0.22356374 | E13: =SUMIFS(Datos!$H$3:$H$1903,Datos!$C$3:$C$1903,$A13) -> 1566 | F13: =IFERROR(B13/E13,0) -> 2805124
A14: 13ultra | B14: =SUMIFS(Datos!$Q$3:$Q$1903,Datos!$C$3:$C$1903,$A14) -> 4269152832 | C14: =SUMIFS(Datos!$S$3:$S$1903,Datos!$C$3:$C$1903,$A14) -> 235752832 | D14: =IFERROR(C14/B14,0) -> 0.055222392 | E14: =SUMIFS(Datos!$H$3:$H$1903,Datos!$C$3:$C$1903,$A14) -> 1204 | F14: =IFERROR(B14/E14,0) -> 3545808
A15: ASPIRE 3 | B15: =SUMIFS(Datos!$Q$3:$Q$1903,Datos!$C$3:$C$1903,$A15) -> 4194947718 | C15: =SUMIFS(Datos!$S$3:$S$1903,Datos!$C$3:$C$1903,$A15) -> 1021547718 | D15: =IFERROR(C15/B15,0) -> 0.24351858 | E15: =SUMIFS(Datos!$H$3:$H$1903,Datos!$C$3:$C$1903,$A15) -> 738 | F15: =IFERROR(B15/E15,0) -> 5684211
... A24: Celular Donalis | B24: =SUMIFS(Datos!$Q$3:$Q$1903,Datos!$C$3:$C$1903,$A24) -> 172631529 | C24: =SUMIFS(Datos!$S$3:$S$1903,Datos!$C$3:$C$1903,$A24) -> 36131529 | D24: =IFERROR(C24/B24,0) -> 0.20929855 | E24: =SUMIFS(Datos!$H$3:$H$1903,Datos!$C$3:$C$1903,$A24) -> 21 | F24: =IFERROR(B24/E24,0) -> 8220549
A26: Ventas por Marca (proveedor)
A27: Marca | B27: Ventas | C27: Utilidad Bruta | D27: Margen % | E27: % del Total
A28: Apple | B28: =SUMIFS(Datos!$Q$3:$Q$1903,Datos!$E$3:$E$1903,$A28) -> 27792445162 | C28: =SUMIFS(Datos!$S$3:$S$1903,Datos!$E$3:$E$1903,$A28) -> 3956089162 | D28: =IFERROR(C28/B28,0) -> 0.14234405 | E28: =IFERROR(B28/SUM(Datos!$Q$3:$Q$1903),0) -> 0.267736
A29: Asus | B29: =SUMIFS(Datos!$Q$3:$Q$1903,Datos!$E$3:$E$1903,$A29) -> 17323637504 | C29: =SUMIFS(Datos!$S$3:$S$1903,Datos!$E$3:$E$1903,$A29) -> 2181045504 | D29: =IFERROR(C29/B29,0) -> 0.12589997 | E29: =IFERROR(B29/SUM(Datos!$Q$3:$Q$1903),0) -> 0.16688569
A30: Lenovo | B30: =SUMIFS(Datos!$Q$3:$Q$1903,Datos!$E$3:$E$1903,$A30) -> 16655742633 | C30: =SUMIFS(Datos!$S$3:$S$1903,Datos!$E$3:$E$1903,$A30) -> 4589842633 | D30: =IFERROR(C30/B30,0) -> 0.27557118 | E30: =IFERROR(B30/SUM(Datos!$Q$3:$Q$1903),0) -> 0.16045159
A31: Xiaomi | B31: =SUMIFS(Datos!$Q$3:$Q$1903,Datos!$E$3:$E$1903,$A31) -> 13079287232 | C31: =SUMIFS(Datos!$S$3:$S$1903,Datos!$E$3:$E$1903,$A31) -> 1372987232 | D31: =IFERROR(C31/B31,0) -> 0.10497416 | E31: =IFERROR(B31/SUM(Datos!$Q$3:$Q$1903),0) -> 0.12599813
A32: Intel | B32: =SUMIFS(Datos!$Q$3:$Q$1903,Datos!$E$3:$E$1903,$A32) -> 9280914346 | C32: =SUMIFS(Datos!$S$3:$S$1903,Datos!$E$3:$E$1903,$A32) -> 895984346 | D32: =IFERROR(C32/B32,0) -> 0.096540525 | E32: =IFERROR(B32/SUM(Datos!$Q$3:$Q$1903),0) -> 0.089406848
A33: Samsum | B33: =SUMIFS(Datos!$Q$3:$Q$1903,Datos!$E$3:$E$1903,$A33) -> 8142409784 | C33: =SUMIFS(Datos!$S$3:$S$1903,Datos!$E$3:$E$1903,$A33) -> 920576024 | D33: =IFERROR(C33/B33,0) -> 0.11305941 | E33: =IFERROR(B33/SUM(Datos!$Q$3:$Q$1903),0) -> 0.078439167
A34: Janus | B34: =SUMIFS(Datos!$Q$3:$Q$1903,Datos!$E$3:$E$1903,$A34) -> 4392824184 | C34: =SUMIFS(Datos!$S$3:$S$1903,Datos!$E$3:$E$1903,$A34) -> 982076184 | D34: =IFERROR(C34/B34,0) -> 0.22356374 | E34: =IFERROR(B34/SUM(Datos!$Q$3:$Q$1903),0) -> 0.042317874
A35: Acer | B35: =SUMIFS(Datos!$Q$3:$Q$1903,Datos!$E$3:$E$1903,$A35) -> 4194947718 | C35: =SUMIFS(Datos!$S$3:$S$1903,Datos!$E$3:$E$1903,$A35) -> 1021547718 | D35: =IFERROR(C35/B35,0) -> 0.24351858 | E35: =IFERROR(B35/SUM(Datos!$Q$3:$Q$1903),0) -> 0.040411649
A36: Vivo | B36: =SUMIFS(Datos!$Q$3:$Q$1903,Datos!$E$3:$E$1903,$A36) -> 2943200000 | C36: =SUMIFS(Datos!$S$3:$S$1903,Datos!$E$3:$E$1903,$A36) -> 339600000 | D36: =IFERROR(C36/B36,0) -> 0.11538462 | E36: =IFERROR(B36/SUM(Datos!$Q$3:$Q$1903),0) -> 0.028353051

Sheet Clientes
A1: Clientes — Concentración de cartera
A2: Solo 4 clientes activos. El % acumulado y el índice HHI cuantifican qué tan expuesta está la empresa a perder uno de ellos.
A3: Cliente | B3: Ciudad | C3: Ventas | D3: % Participación | E3: % Acumulado | F3: Transacciones
A4: Asociados LTDA | B4: Bogotá | C4: =SUMIFS(Datos!$Q$3:$Q$1903,Datos!$J$3:$J$1903,$A4) -> 43739616368 | D4: =IFERROR(C4/SUM(Datos!$Q$3:$Q$1903),0) -> 0.42136163 | E4: =SUM($D$4:D4) -> 0.42136163 | F4: =COUNTIFS(Datos!$J$3:$J$1903,$A4) -> 804
A5: Smart S.A.S | B5: Medellín | C5: =SUMIFS(Datos!$Q$3:$Q$1903,Datos!$J$3:$J$1903,$A5) -> 20886432096 | D5: =IFERROR(C5/SUM(Datos!$Q$3:$Q$1903),0) -> 0.20120755 | E5: =SUM($D$4:D5) -> 0.62256918 | F5: =COUNTIFS(Datos!$J$3:$J$1903,$A5) -> 378
A6: FullStark | B6: Bucaramanga | C6: =SUMIFS(Datos!$Q$3:$Q$1903,Datos!$J$3:$J$1903,$A6) -> 19664001853 | D6: =IFERROR(C6/SUM(Datos!$Q$3:$Q$1903),0) -> 0.18943138 | E6: =SUM($D$4:D6) -> 0.81200056 | F6: =COUNTIFS(Datos!$J$3:$J$1903,$A6) -> 353
A7: Distribuidora Oriente | B7: Cali | C7: =SUMIFS(Datos!$Q$3:$Q$1903,Datos!$J$3:$J$1903,$A7) -> 19515358246 | D7: =IFERROR(C7/SUM(Datos!$Q$3:$Q$1903),0) -> 0.18799944 | E7: =SUM($D$4:D7) -> 1 | F7: =COUNTIFS(Datos!$J$3:$J$1903,$A7) -> 366
A10: Índice de concentración HHI (Herfindahl-Hirschman) | C10: =SUMPRODUCT($D$4:$D$7,$D$4:$D$7) -> 0.28925814
A11: Lectura: HHI > 0,25 se considera alta concentración (equivalente a tener 4 o menos clientes de peso similar).

Sheet Vendedores
A1: Vendedores — Desempeño comercial
A2: Base objetiva para evaluar comisiones y detectar brechas de desempeño entre el equipo comercial.
A3: Empleado | B3: Ventas | C3: Utilidad Bruta | D3: Transacciones | E3: Ticket Promedio | F3: Margen % | G3: Ranking
A4: Diego | B4: =SUMIFS(Datos!$Q$3:$Q$1903,Datos!$N$3:$N$1903,$A4) -> 12468916035 | C4: =SUMIFS(Datos!$S$3:$S$1903,Datos!$N$3:$N$1903,$A4) -> 1936963075 | D4: =COUNTIFS(Datos!$N$3:$N$1903,$A4) -> 205 | E4: =IFERROR(B4/D4,0) -> 60823981 | F4: =IFERROR(C4/B4,0) -> 0.15534334 | G4: =RANK(B4,$B$4:$B$13) -> 1
A5: Matias | B5: =SUMIFS(Datos!$Q$3:$Q$1903,Datos!$N$3:$N$1903,$A5) -> 11001412676 | C5: =SUMIFS(Datos!$S$3:$S$1903,Datos!$N$3:$N$1903,$A5) -> 1630615156 | D5: =COUNTIFS(Datos!$N$3:$N$1903,$A5) -> 202 | E5: =IFERROR(B5/D5,0) -> 54462439 | F5: =IFERROR(C5/B5,0) -> 0.14821871 | G5: =RANK(B5,$B$4:$B$13) -> 2
A6: Liliana | B6: =SUMIFS(Datos!$Q$3:$Q$1903,Datos!$N$3:$N$1903,$A6) -> 10813613563 | C6: =SUMIFS(Datos!$S$3:$S$1903,Datos!$N$3:$N$1903,$A6) -> 1643451803 | D6: =COUNTIFS(Datos!$N$3:$N$1903,$A6) -> 197 | E6: =IFERROR(B6/D6,0) -> 54891439 | F6: =IFERROR(C6/B6,0) -> 0.15197989 | G6: =RANK(B6,$B$4:$B$13) -> 3
A7: Alejandra | B7: =SUMIFS(Datos!$Q$3:$Q$1903,Datos!$N$3:$N$1903,$A7) -> 10746481941 | C7: =SUMIFS(Datos!$S$3:$S$1903,Datos!$N$3:$N$1903,$A7) -> 1698004461 | D7: =COUNTIFS(Datos!$N$3:$N$1903,$A7) -> 182 | E7: =IFERROR(B7/D7,0) -> 59046604 | F7: =IFERROR(C7/B7,0) -> 0.15800561 | G7: =RANK(B7,$B$4:$B$13) -> 4
A8: Martha | B8: =SUMIFS(Datos!$Q$3:$Q$1903,Datos!$N$3:$N$1903,$A8) -> 10489264790 | C8: =SUMIFS(Datos!$S$3:$S$1903,Datos!$N$3:$N$1903,$A8) -> 1598975230 | D8: =COUNTIFS(Datos!$N$3:$N$1903,$A8) -> 211 | E8: =IFERROR(B8/D8,0) -> 49712155 | F8: =IFERROR(C8/B8,0) -> 0.15243921 | G8: =RANK(B8,$B$4:$B$13) -> 5
A9: Juan | B9: =SUMIFS(Datos!$Q$3:$Q$1903,Datos!$N$3:$N$1903,$A9) -> 10240320591 | C9: =SUMIFS(Datos!$S$3:$S$1903,Datos!$N$3:$N$1903,$A9) -> 1671430991 | D9: =COUNTIFS(Datos!$N$3:$N$1903,$A9) -> 184 | E9: =IFERROR(B9/D9,0) -> 55653916 | F9: =IFERROR(C9/B9,0) -> 0.16322057 | G9: =RANK(B9,$B$4:$B$13) -> 6
A10: Hernan | B10: =SUMIFS(Datos!$Q$3:$Q$1903,Datos!$N$3:$N$1903,$A10) -> 9927646495 | C10: =SUMIFS(Datos!$S$3:$S$1903,Datos!$N$3:$N$1903,$A10) -> 1579910775 | D10: =COUNTIFS(Datos!$N$3:$N$1903,$A10) -> 183 | E10: =IFERROR(B10/D10,0) -> 54249434 | F10: =IFERROR(C10/B10,0) -> 0.15914253 | G10: =RANK(B10,$B$4:$B$13) -> 7
A11: Daniela | B11: =SUMIFS(Datos!$Q$3:$Q$1903,Datos!$N$3:$N$1903,$A11) -> 9457100593 | C11: =SUMIFS(Datos!$S$3:$S$1903,Datos!$N$3:$N$1903,$A11) -> 1451827593 | D11: =COUNTIFS(Datos!$N$3:$N$1903,$A11) -> 187 | E11: =IFERROR(B11/D11,0) -> 50572730 | F11: =IFERROR(C11/B11,0) -> 0.1535172 | G11: =RANK(B11,$B$4:$B$13) -> 8
A12: Lina | B12: =SUMIFS(Datos!$Q$3:$Q$1903,Datos!$N$3:$N$1903,$A12) -> 9441530676 | C12: =SUMIFS(Datos!$S$3:$S$1903,Datos!$N$3:$N$1903,$A12) -> 1567326476 | D12: =COUNTIFS(Datos!$N$3:$N$1903,$A12) -> 182 | E12: =IFERROR(B12/D12,0) -> 51876542 | F12: =IFERROR(C12/B12,0) -> 0.16600343 | G12: =RANK(B12,$B$4:$B$13) -> 9
A13: Paola | B13: =SUMIFS(Datos!$Q$3:$Q$1903,Datos!$N$3:$N$1903,$A13) -> 9219121203 | C13: =SUMIFS(Datos!$S$3:$S$1903,Datos!$N$3:$N$1903,$A13) -> 1481243243 | D13: =COUNTIFS(Datos!$N$3:$N$1903,$A13) -> 168 | E13: =IFERROR(B13/D13,0) -> 54875721 | F13: =IFERROR(C13/B13,0) -> 0.16067076 | G13: =RANK(B13,$B$4:$B$13) -> 10

Sheet Segmentacion
A1: Segmentación — Ciudad, transporte, tipo de cliente y forma de pago
A2: Cruces operativos y de riesgo: dependencia logística y exposición a crédito.
A4: Por ciudad
A5: Categoría | B5: Ventas | C5: % del Total | D5: Transacciones
A6: Bogotá | B6: =SUMIFS(Datos!$Q$3:$Q$1903,Datos!$K$3:$K$1903,$A6) -> 43739616368 | C6: =IFERROR(B6/SUM(Datos!$Q$3:$Q$1903),0) -> 0.42136163 | D6: =COUNTIFS(Datos!$K$3:$K$1903,$A6) -> 804
A7: Medellín | B7: =SUMIFS(Datos!$Q$3:$Q$1903,Datos!$K$3:$K$1903,$A7) -> 20886432096 | C7: =IFERROR(B7/SUM(Datos!$Q$3:$Q$1903),0) -> 0.20120755 | D7: =COUNTIFS(Datos!$K$3:$K$1903,$A7) -> 378
A8: Bucaramanga | B8: =SUMIFS(Datos!$Q$3:$Q$1903,Datos!$K$3:$K$1903,$A8) -> 19664001853 | C8: =IFERROR(B8/SUM(Datos!$Q$3:$Q$1903),0) -> 0.18943138 | D8: =COUNTIFS(Datos!$K$3:$K$1903,$A8) -> 353
A9: Cali | B9: =SUMIFS(Datos!$Q$3:$Q$1903,Datos!$K$3:$K$1903,$A9) -> 19515358246 | C9: =IFERROR(B9/SUM(Datos!$Q$3:$Q$1903),0) -> 0.18799944 | D9: =COUNTIFS(Datos!$K$3:$K$1903,$A9) -> 366
A12: Por transportadora
A13: Categoría | B13: Ventas | C13: % del Total | D13: Transacciones
A14: Terrestre | B14: =SUMIFS(Datos!$Q$3:$Q$1903,Datos!$L$3:$L$1903,$A14) -> 63254974614 | C14: =IFERROR(B14/SUM(Datos!$Q$3:$Q$1903),0) -> 0.60936107 | D14: =COUNTIFS(Datos!$L$3:$L$1903,$A14) -> 1170
A15: Fluvial | B15: =SUMIFS(Datos!$Q$3:$Q$1903,Datos!$L$3:$L$1903,$A15) -> 20886432096 | C15: =IFERROR(B15/SUM(Datos!$Q$3:$Q$1903),0) -> 0.20120755 | D15: =COUNTIFS(Datos!$L$3:$L$1903,$A15) -> 378
A16: Aereo | B16: =SUMIFS(Datos!$Q$3:$Q$1903,Datos!$L$3:$L$1903,$A16) -> 19664001853 | C16: =IFERROR(B16/SUM(Datos!$Q$3:$Q$1903),0) -> 0.18943138 | D16: =COUNTIFS(Datos!$L$3:$L$1903,$A16) -> 353
A19: Por tipo de cliente
A20: Categoría | B20: Ventas | C20: % del Total | D20: Transacciones
A21: A | B21: =SUMIFS(Datos!$Q$3:$Q$1903,Datos!$M$3:$M$1903,$A21) -> 64668598160 | C21: =IFERROR(B21/SUM(Datos!$Q$3:$Q$1903),0) -> 0.62297908 | D21: =COUNTIFS(Datos!$M$3:$M$1903,$A21) -> 1183
A22: B | B22: =SUMIFS(Datos!$Q$3:$Q$1903,Datos!$M$3:$M$1903,$A22) -> 19664001853 | C22: =IFERROR(B22/SUM(Datos!$Q$3:$Q$1903),0) -> 0.18943138 | D22: =COUNTIFS(Datos!$M$3:$M$1903,$A22) -> 353
A23: C | B23: =SUMIFS(Datos!$Q$3:$Q$1903,Datos!$M$3:$M$1903,$A23) -> 19472808550 | C23: =IFERROR(B23/SUM(Datos!$Q$3:$Q$1903),0) -> 0.18758954 | D23: =COUNTIFS(Datos!$M$3:$M$1903,$A23) -> 365
A26: Por forma de pago
A27: Categoría | B27: Ventas | C27: % del Total | D27: Transacciones
A28: Crédito | B28: =SUMIFS(Datos!$Q$3:$Q$1903,Datos!$I$3:$I$1903,$A28) -> 84141406710 | C28: =IFERROR(B28/SUM(Datos!$Q$3:$Q$1903),0) -> 0.81056862 | D28: =COUNTIFS(Datos!$I$3:$I$1903,$A28) -> 1548
A29: Contado | B29: =SUMIFS(Datos!$Q$3:$Q$1903,Datos!$I$3:$I$1903,$A29) -> 19664001853 | C29: =IFERROR(B29/SUM(Datos!$Q$3:$Q$1903),0) -> 0.18943138 | D29: =COUNTIFS(Datos!$I$3:$I$1903,$A29) -> 353

Sheet Ratios Financieros
A1: Ratios Financieros — Panel ejecutivo
A2: Todos los valores están enlazados (verde) a las demás hojas: se recalculan solos si cambian los datos.
A4: Indicador | B4: Valor | C4: Semáforo | D4: Por qué importa
A5: Ventas totales | B5: =SUM(Datos!$Q$3:$Q$1903) -> 103805408563 | D5: Ingreso total facturado en el período analizado.
A6: Utilidad bruta total | B6: =SUM(Datos!$S$3:$S$1903) -> 16259748803 | D6: Lo que queda tras cubrir el costo de los productos vendidos.
A7: Margen bruto global | B7: =B6/B5 -> 0.15663682 | C7: =IF(B7<0.2,"⚠ Riesgo","OK") -> ⚠ Riesgo | D7: Rentabilidad real del negocio; un margen bajo deja poco margen de error ante descuentos o alzas de costo.
A8: Ticket promedio | B8: =AVERAGE(Datos!$Q$3:$Q$1903) -> 54605686 | D8: Tamaño típico de una venta; sirve para proyectar caja e informar metas comerciales.
A9: Transacciones totales | B9: =COUNT(Datos!$Q$3:$Q$1903) -> 1901 | D9: Volumen de operación del período.
A10: Participación crédito | B10: =Segmentacion!C28 -> 0.81056862 | C10: =IF(B10>0.6,"⚠ Riesgo","OK") -> ⚠ Riesgo | D10: Porcentaje de ventas cobradas a plazo; una cifra alta presiona el capital de trabajo.
A11: Concentración top cliente | B11: =MAX(Clientes!D4:D7) -> 0.42136163 | C11: =IF(B11>0.3,"⚠ Riesgo","OK") -> ⚠ Riesgo | D11: Parte del ingreso que depende de un solo cliente; alto = riesgo de dependencia.
A12: Índice HHI de clientes | B12: =Clientes!C10 -> 0.28925814 | C12: =IF(B12>0.25,"⚠ Riesgo","OK") -> ⚠ Riesgo | D12: Mide la concentración de toda la cartera de clientes en un solo número (>0,25 = alta).
A13: Variación mensual promedio | B13: =SLOPE('Ventas Mensuales'!G4:G15,'Ventas Mensuales'!I4:I15)/AVERAGE('Ventas Mensuales'!G4:G15) -> -0.0084067663 | C13: =IF(B13<-0.1,"⚠ Riesgo","OK") -> OK | D13: Pendiente de la tendencia de ventas normalizada; negativo indica ventas en descenso mes a mes.
A14: Participación Portátiles | B14: =SUMIFS(Datos!$Q$3:$Q$1903,Datos!$D$3:$D$1903,"Portátil")/B5 -> 0.45324421 | D14: Peso de la línea de producto más relevante en el ingreso total.

Sheet Alertas Margen
A1: Alertas de margen por producto
A2: Celdas amarillas = supuestos editables. Utilidad no capturada = (margen objetivo − margen real) × ventas, solo si el margen real es menor.
A3: Margen objetivo | B3: 0.15 | C3: Supuesto del analista (cercano al margen global de 15,7%); modificar libremente.
A4: Margen crítico | B4: 0.1 | C4: Por debajo de este valor el producto se marca CRÍTICO.
A6: Producto | B6: Ventas | C6: Margen % | D6: Estado | E6: Utilidad no capturada | F6: % de ventas totales
A7: ='Producto y Marca'!A4 -> Lenovo 14IGL7 | B7: ='Producto y Marca'!B4 -> 9897540996 | C7: ='Producto y Marca'!D4 -> 0.20929855 | D7: =IF(C7<$B$4,"CRÍTICO",IF(C7<$B$3,"Vigilar","OK")) -> OK | E7: =MAX(0,($B$3-C7)*B7) -> 0 | F7: =IFERROR(B7/'Ratios Financieros'!$B$5,0) -> 0.095347065
A8: ='Producto y Marca'!A5 -> MacBook Pro | B8: ='Producto y Marca'!B5 -> 9468071808 | C8: ='Producto y Marca'!D5 -> 0.079956281 | D8: =IF(C8<$B$4,"CRÍTICO",IF(C8<$B$3,"Vigilar","OK")) -> CRÍTICO | E8: =MAX(0,($B$3-C8)*B8) -> 6.6317896e+08 | F8: =IFERROR(B8/'Ratios Financieros'!$B$5,0) -> 0.091209812
A9: ='Producto y Marca'!A6 -> ASUS AIO V | B9: ='Producto y Marca'!B6 -> 8806137912 | C9: ='Producto y Marca'!D6 -> 0.098288934 | D9: =IF(C9<$B$4,"CRÍTICO",IF(C9<$B$3,"Vigilar","OK")) -> CRÍTICO | E9: =MAX(0,($B$3-C9)*B9) -> 4.5537477e+08 | F9: =IFERROR(B9/'Ratios Financieros'!$B$5,0) -> 0.084833132
A10: ='Producto y Marca'!A7 -> Gaming F15 | B10: ='Producto y Marca'!B7 -> 8517499592 | C10: ='Producto y Marca'!D7 -> 0.15444669 | D10: =IF(C10<$B$4,"CRÍTICO",IF(C10<$B$3,"Vigilar","OK")) -> OK | E10: =MAX(0,($B$3-C10)*B10) -> 0 | F10: =IFERROR(B10/'Ratios Financieros'!$B$5,0) -> 0.082052561
A11: ='Producto y Marca'!A8 -> 15 Pulgadas Ip1 Athlon | B11: ='Producto y Marca'!B8 -> 6585570108 | C11: ='Producto y Marca'!D8 -> 0.37691044 | D11: =IF(C11<$B$4,"CRÍTICO",IF(C11<$B$3,"Vigilar","OK")) -> OK | E11: =MAX(0,($B$3-C11)*B11) -> 0 | F11: =IFERROR(B11/'Ratios Financieros'!$B$5,0) -> 0.063441493
A12: ='Producto y Marca'!A9 -> Xiaomi redmi 8 | B12: ='Producto y Marca'!B9 -> 6367914400 | C12: ='Producto y Marca'!D9 -> 0.13346825 | D12: =IF(C12<$B$4,"CRÍTICO",IF(C12<$B$3,"Vigilar","OK")) -> Vigilar | E12: =MAX(0,($B$3-C12)*B12) -> 105272760 | F12: =IFERROR(B12/'Ratios Financieros'!$B$5,0) -> 0.061344727
A13: ='Producto y Marca'!A10 -> MacBook Air | B13: ='Producto y Marca'!B10 -> 6033325368 | C13: ='Producto y Marca'!D10 -> 0.14210229 | D13: =IF(C13<$B$4,"CRÍTICO",IF(C13<$B$3,"Vigilar","OK")) -> Vigilar | E13: =MAX(0,($B$3-C13)*B13) -> 47649437 | F13: =IFERROR(B13/'Ratios Financieros'!$B$5,0) -> 0.058121493
A14: ='Producto y Marca'!A11 -> Intel Corei7 | B14: ='Producto y Marca'!B11 -> 5161483346 | C14: ='Producto y Marca'!D11 -> 0.054492735 | D14: =IF(C14<$B$4,"CRÍTICO",IF(C14<$B$3,"Vigilar","OK")) -> CRÍTICO | E14: =MAX(0,($B$3-C14)*B14) -> 4.9295916e+08 | F14: =IFERROR(B14/'Ratios Financieros'!$B$5,0) -> 0.049722682
A15: ='Producto y Marca'!A12 -> Galaxy jpro | B15: ='Producto y Marca'!B12 -> 4949845104 | C15: ='Producto y Marca'!D12 -> 0.17066622 | D15: =IF(C15<$B$4,"CRÍTICO",IF(C15<$B$3,"Vigilar","OK")) -> OK | E15: =MAX(0,($B$3-C15)*B15) -> 0 | F15: =IFERROR(B15/'Ratios Financieros'!$B$5,0) -> 0.047683884
A16: ='Producto y Marca'!A13 -> JANUS | B16: ='Producto y Marca'!B13 -> 4392824184 | C16: ='Producto y Marca'!D13 -> 0.22356374 | D16: =IF(C16<$B$4,"CRÍTICO",IF(C16<$B$3,"Vigilar","OK")) -> OK | E16: =MAX(0,($B$3-C16)*B16) -> 0 | F16: =IFERROR(B16/'Ratios Financieros'!$B$5,0) -> 0.042317874
A17: ='Producto y Marca'!A14 -> 13ultra | B17: ='Producto y Marca'!B14 -> 4269152832 | C17: ='Producto y Marca'!D14 -> 0.055222392 | D17: =IF(C17<$B$4,"CRÍTICO",IF(C17<$B$3,"Vigilar","OK")) -> CRÍTICO | E17: =MAX(0,($B$3-C17)*B17) -> 4.0462009e+08 | F17: =IFERROR(B17/'Ratios Financieros'!$B$5,0) -> 0.041126497
A18: ='Producto y Marca'!A15 -> ASPIRE 3 | B18: ='Producto y Marca'!B15 -> 4194947718 | C18: ='Producto y Marca'!D15 -> 0.24351858 | D18: =IF(C18<$B$4,"CRÍTICO",IF(C18<$B$3,"Vigilar","OK")) -> OK | E18: =MAX(0,($B$3-C18)*B18) -> 0 | F18: =IFERROR(B18/'Ratios Financieros'!$B$5,0) -> 0.040411649
... A27: ='Producto y Marca'!A24 -> Celular Donalis | B27: ='Producto y Marca'!B24 -> 172631529 | C27: ='Producto y Marca'!D24 -> 0.20929855 | D27: =IF(C27<$B$4,"CRÍTICO",IF(C27<$B$3,"Vigilar","OK")) -> OK | E27: =MAX(0,($B$3-C27)*B27) -> 0 | F27: =IFERROR(B27/'Ratios Financieros'!$B$5,0) -> 0.0016630302
A28: Total | D28: =COUNTIF(D7:D27,"CRÍTICO")&" críticos" -> 5 críticos | E28: =SUM(E7:E27) -> 2.7753505e+09

Sheet Escenarios
A1: Escenarios — Impacto en utilidad
A2: Base = ventas y margen reales 2022. Celdas amarillas (Δ margen en puntos, Δ ventas %) son supuestos editables.
A4: Escenario | B4: Δ Margen (pts) | C4: Δ Ventas % | D4: Ventas | E4: Margen % | F4: Utilidad Bruta | G4: Δ Utilidad vs base
A5: Base 2022 | B5: 0 | C5: 0 | D5: ='Ratios Financieros'!$B$5*(1+C5) -> 103805408563 | E5: ='Ratios Financieros'!$B$7+B5 -> 0.15663682 | F5: =D5*E5 -> 16259748803 | G5: =F5-$F$5 -> 0
A6: Margen +1 punto | B6: 0.01 | C6: 0 | D6: ='Ratios Financieros'!$B$5*(1+C6) -> 103805408563 | E6: ='Ratios Financieros'!$B$7+B6 -> 0.16663682 | F6: =D6*E6 -> 1.7297803e+10 | G6: =F6-$F$5 -> 1.0380541e+09
A7: Margen +2 puntos | B7: 0.02 | C7: 0 | D7: ='Ratios Financieros'!$B$5*(1+C7) -> 103805408563 | E7: ='Ratios Financieros'!$B$7+B7 -> 0.17663682 | F7: =D7*E7 -> 1.8335857e+10 | G7: =F7-$F$5 -> 2.0761082e+09
A8: Ventas −10% | B8: 0 | C8: -0.1 | D8: ='Ratios Financieros'!$B$5*(1+C8) -> 9.3424868e+10 | E8: ='Ratios Financieros'!$B$7+B8 -> 0.15663682 | F8: =D8*E8 -> 1.4633774e+10 | G8: =F8-$F$5 -> -1.6259749e+09
A9: Ventas −10% y margen +2 pts | B9: 0.02 | C9: -0.1 | D9: ='Ratios Financieros'!$B$5*(1+C9) -> 9.3424868e+10 | E9: ='Ratios Financieros'!$B$7+B9 -> 0.17663682 | F9: =D9*E9 -> 1.6502271e+10 | G9: =F9-$F$5 -> 2.4252247e+08
A10: Ventas +10% | B10: 0 | C10: 0.1 | D10: ='Ratios Financieros'!$B$5*(1+C10) -> 1.1418595e+11 | E10: ='Ratios Financieros'!$B$7+B10 -> 0.15663682 | F10: =D10*E10 -> 1.7885724e+10 | G10: =F10-$F$5 -> 1.6259749e+09
A12: Lectura: compara filas entre sí; un punto de margen equivale a 1% de las ventas base. No es una previsión, es un análisis de sensibilidad.

Sheet Estacionalidad
A1: Estacionalidad — Trimestres e índice mensual
A2: Usa ventas normalizadas (diciembre a 30 días). Con un solo año de datos, la estacionalidad es indicativa, no concluyente.
A4: Trimestre | B4: Ventas | C4: % del total
A5: T1 2022 | B5: =SUM('Ventas Mensuales'!G4:G6) -> 26546067670 | C5: =B5/SUM($B$5:$B$8) -> 0.24365901
A6: T2 2022 | B6: =SUM('Ventas Mensuales'!G7:G9) -> 32922779660 | C6: =B6/SUM($B$5:$B$8) -> 0.30218909
A7: T3 2022 | B7: =SUM('Ventas Mensuales'!G10:G12) -> 21169170830 | C7: =B7/SUM($B$5:$B$8) -> 0.19430596
A8: T4 2022 | B8: =SUM('Ventas Mensuales'!G13:G15) -> 2.8309594e+10 | C8: =B8/SUM($B$5:$B$8) -> 0.25984593
A11: Mes | B11: Ventas normalizadas | C11: Índice vs promedio
A12: ='Ventas Mensuales'!A4 -> 2022-01 | B12: ='Ventas Mensuales'!G4 -> 9738965526 | C12: =B12/AVERAGE($B$12:$B$23) -> 1.0726953
A13: ='Ventas Mensuales'!A5 -> 2022-02 | B13: ='Ventas Mensuales'!G5 -> 7667494170 | C13: =B13/AVERAGE($B$12:$B$23) -> 0.8445337
A14: ='Ventas Mensuales'!A6 -> 2022-03 | B14: ='Ventas Mensuales'!G6 -> 9139607974 | C14: =B14/AVERAGE($B$12:$B$23) -> 1.0066792
A15: ='Ventas Mensuales'!A7 -> 2022-04 | B15: ='Ventas Mensuales'!G7 -> 11045631654 | C15: =B15/AVERAGE($B$12:$B$23) -> 1.2166176
A16: ='Ventas Mensuales'!A8 -> 2022-05 | B16: ='Ventas Mensuales'!G8 -> 13800339040 | C16: =B16/AVERAGE($B$12:$B$23) -> 1.5200339
A17: ='Ventas Mensuales'!A9 -> 2022-06 | B17: ='Ventas Mensuales'!G9 -> 8076808966 | C17: =B17/AVERAGE($B$12:$B$23) -> 0.88961755
A18: ='Ventas Mensuales'!A10 -> 2022-07 | B18: ='Ventas Mensuales'!G10 -> 5985626746 | C18: =B18/AVERAGE($B$12:$B$23) -> 0.65928495
A19: ='Ventas Mensuales'!A11 -> 2022-08 | B19: ='Ventas Mensuales'!G11 -> 7802299454 | C19: =B19/AVERAGE($B$12:$B$23) -> 0.85938179
A20: ='Ventas Mensuales'!A12 -> 2022-09 | B20: ='Ventas Mensuales'!G12 -> 7381244630 | C20: =B20/AVERAGE($B$12:$B$23) -> 0.81300484
A21: ='Ventas Mensuales'!A13 -> 2022-10 | B21: ='Ventas Mensuales'!G13 -> 8688965074 | C21: =B21/AVERAGE($B$12:$B$23) -> 0.95704329
A22: ='Ventas Mensuales'!A14 -> 2022-11 | B22: ='Ventas Mensuales'!G14 -> 9978997204 | C22: =B22/AVERAGE($B$12:$B$23) -> 1.0991335
A23: ='Ventas Mensuales'!A15 -> 2022-12 | B23: ='Ventas Mensuales'!G15 -> 9.6416317e+09 | C23: =B23/AVERAGE($B$12:$B$23) -> 1.0619744
A25: Índice 1,00 = mes promedio; >1 = mes fuerte, <1 = mes débil.
